{
  "main": {
    "id": "c00b1ed13923bb47",
    "type": "split",
    "children": [
      {
        "id": "8e5f318c209f07ff",
        "type": "tabs",
        "children": [
          {
            "id": "39d72fdb83d808d5",
            "type": "leaf",
            "state": {
              "type": "markdown",
              "state": {
                "file": "Module 2/2.2 - Heap Memory.md",
                "mode": "source",
                "source": false
              }
            }
          }
        ]
      }
    ],
    "direction": "vertical"
  },
  "left": {
    "id": "c2954979097d2b67",
    "type": "split",
    "children": [
      {
        "id": "17f5b9850ad6e062",
        "type": "tabs",
        "children": [
          {
            "id": "b60f5963fab058f5",
            "type": "leaf",
            "state": {
              "type": "file-explorer",
              "state": {
                "sortOrder": "alphabetical"
              }
            }
          },
          {
            "id": "3641dd9c5c96db44",
            "type": "leaf",
            "state": {
              "type": "search",
              "state": {
                "query": "",
                "matchingCase": false,
                "explainSearch": false,
                "collapseAll": false,
                "extraContext": false,
                "sortOrder": "alphabetical"
              }
            }
          },
          {
            "id": "b5c1d1bbc45fd7c0",
            "type": "leaf",
            "state": {
              "type": "bookmarks",
              "state": {}
            }
          }
        ]
      }
    ],
    "direction": "horizontal",
    "width": 300
  },
  "right": {
    "id": "b037b4718a3e3f9b",
    "type": "split",
    "children": [
      {
        "id": "f83782cba4c252cb",
        "type": "tabs",
        "children": [
          {
            "id": "e846cc74aa2b1530",
            "type": "leaf",
            "state": {
              "type": "backlink",
              "state": {
                "file": "Module 2/2.2 - Heap Memory.md",
                "collapseAll": false,
                "extraContext": false,
                "sortOrder": "alphabetical",
                "showSearch": false,
                "searchQuery": "",
                "backlinkCollapsed": false,
                "unlinkedCollapsed": true
              }
            }
          },
          {
            "id": "f8671836d34ad0c8",
            "type": "leaf",
            "state": {
              "type": "outgoing-link",
              "state": {
                "file": "Module 2/2.2 - Heap Memory.md",
                "linksCollapsed": false,
                "unlinkedCollapsed": true
              }
            }
          },
          {
            "id": "551da07565ceac74",
            "type": "leaf",
            "state": {
              "type": "tag",
              "state": {
                "sortOrder": "frequency",
                "useHierarchy": true
              }
            }
          },
          {
            "id": "5ec2c1560bfa77b9",
            "type": "leaf",
            "state": {
              "type": "outline",
              "state": {
                "file": "Module 2/2.2 - Heap Memory.md"
              }
            }
          }
        ]
      }
    ],
    "direction": "horizontal",
    "width": 300,
    "collapsed": true
  },
  "left-ribbon": {
    "hiddenItems": {
      "switcher:Open quick switcher": false,
      "graph:Open graph view": false,
      "canvas:Create new canvas": false,
      "daily-notes:Open today's daily note": false,
      "templates:Insert template": false,
      "command-palette:Open command palette": false
    }
  },
  "active": "39d72fdb83d808d5",
  "lastOpenFiles": [
    "images/Untitled.md",
    "images/Pasted image 20241012115907.png",
    "images/Pasted image 20241012115919.png",
    "images/Pasted image 20241012121437.png",
    "images/Pasted image 20241012121908.png",
    "images/Pasted image 20241012123250.png",
    "Pasted image 20241012123250.png",
    "Pasted image 20241012121908.png",
    "Pasted image 20241012121437.png",
    "Pasted image 20241012115919.png",
    "Pasted image 20241012115907.png",
    "Untitled.md",
    "Module 2/2.2 - Heap Memory.md",
    "Module 2/2.1 - Stack Memory.md",
    "images",
    "New folder",
    "Module 1/1.3 - Standard Library.md",
    "Module 2",
    "programs/hello_world/hello_world.o",
    "programs/hello_world/hello_world.cpp",
    "programs/hello_world",
    "hello_world/hello_world.o",
    "hello_world/hello_world.cpp",
    "hello_world",
    "Module 1/1.2 - Classes.md",
    "Module 1/1.1 - Types and Programs.md",
    "Evaluation/C++ Evaluation Test for Graduate Training (Oct 10, 2024).md",
    "Evaluation/Answers.md",
    "Answers.md",
    "Evaluation",
    "C++ Evaluation Test for Graduate Training (Oct 10, 2024).md",
    "Welcome.md"
  ]
}